depthai_hand_tracker/FPS.py
depthai_hand_tracker/HandTracker.py
depthai_hand_tracker/HandTrackerBpf.py
depthai_hand_tracker/HandTrackerBpfEdge.py
depthai_hand_tracker/HandTrackerEdge.py
depthai_hand_tracker/HandTrackerRenderer.py
depthai_hand_tracker/__init__.py
depthai_hand_tracker/demo.py
depthai_hand_tracker/demo_bpf.py
depthai_hand_tracker/mediapipe_utils.py
depthai_hand_tracker/print_dirs.py
depthai_hand_tracker/template_manager_script_bpf_duo.py
depthai_hand_tracker/template_manager_script_bpf_solo.py
depthai_hand_tracker/template_manager_script_duo.py
depthai_hand_tracker/template_manager_script_solo.py
depthai_hand_tracker/custom_models/PDPostProcessing_top2_sh1.blob
depthai_hand_tracker/models/hand_landmark_080_sh4.blob
depthai_hand_tracker/models/hand_landmark_full_sh4.blob
depthai_hand_tracker/models/hand_landmark_lite_sh4.blob
depthai_hand_tracker/models/hand_landmark_sparse_sh4.blob
depthai_hand_tracker/models/movenet_singlepose_lightning_U8_transpose.blob
depthai_hand_tracker/models/movenet_singlepose_thunder_U8_transpose.blob
depthai_hand_tracker/models/palm_detection_sh4.blob
depthai_hand_tracker-2.0.1.dist-info/METADATA
depthai_hand_tracker-2.0.1.dist-info/WHEEL
depthai_hand_tracker-2.0.1.dist-info/top_level.txt
depthai_hand_tracker-2.0.1.dist-info/RECORD
