Metadata-Version: 2.1
Name: depthai-hand-tracker
Version: 2.0.1
Summary: Depthai Hand Tracker
Home-page: https://github.com/geaxgx/depthai_hand_tracker
Author: geaxgx
Author-email: 
Requires-Dist: opencv-python (>=4.5.1.48)
Requires-Dist: depthai (>=2.13)
